virt/firmware/__init__.py
virt/firmware/dump.py
virt/firmware/host.py
virt/firmware/measure.py
virt/firmware/migrate.py
virt/firmware/misc.py
virt/firmware/sigdb.py
virt/firmware/vars.py
virt/firmware/aws/dict.v0
virt/firmware/bootcfg/__init__.py
virt/firmware/bootcfg/addons.py
virt/firmware/bootcfg/bootcfg.py
virt/firmware/bootcfg/linuxcfg.py
virt/firmware/bootcfg/main.py
virt/firmware/bootcfg/menu.py
virt/firmware/certs/centos.org/centos-2018.pem
virt/firmware/certs/centos.org/centos-2020.pem
virt/firmware/certs/debian.org/debian-2016.pem
virt/firmware/certs/fedoraproject.org/fedora-2020.pem
virt/firmware/certs/microsoft.com/ms-kek-2011.pem
virt/firmware/certs/microsoft.com/ms-kek-2023.pem
virt/firmware/certs/microsoft.com/ms-uefi-2011.pem
virt/firmware/certs/microsoft.com/ms-uefi-2023.pem
virt/firmware/certs/microsoft.com/ms-uefi-rom-2023.pem
virt/firmware/certs/microsoft.com/windows-2011.pem
virt/firmware/certs/microsoft.com/windows-2023.pem
virt/firmware/certs/redhat.com/redhat-2014.pem
virt/firmware/certs/redhat.com/redhat-2020.pem
virt/firmware/certs/redhat.com/redhat-2023.pem
virt/firmware/certs/redhat.com/redhat-test-insecure-2012.pem
virt/firmware/certs/redhat.com/rh-pk-kek-2014.pem
virt/firmware/certs/redhat.com/rh-uefi-2024.pem
virt/firmware/certs/ubuntu.com/ubuntu-2012.pem
virt/firmware/efi/__init__.py
virt/firmware/efi/bootentry.py
virt/firmware/efi/certs.py
virt/firmware/efi/devpath.py
virt/firmware/efi/efijson.py
virt/firmware/efi/efivar.py
virt/firmware/efi/guids.py
virt/firmware/efi/siglist.py
virt/firmware/efi/ucs16.py
virt/firmware/varstore/__init__.py
virt/firmware/varstore/authfiles.py
virt/firmware/varstore/autodetect.py
virt/firmware/varstore/aws.py
virt/firmware/varstore/edk2.py
virt/firmware/varstore/jstore.py
virt/firmware/varstore/linux.py
virt/peutils/__init__.py
virt/peutils/pedecode.py
virt/peutils/pesign.py
virt/peutils/peutils.py
virt_firmware-25.12.dist-info/licenses/LICENSE
virt_firmware-25.12.dist-info/METADATA
virt_firmware-25.12.dist-info/WHEEL
virt_firmware-25.12.dist-info/entry_points.txt
virt_firmware-25.12.dist-info/top_level.txt
virt_firmware-25.12.dist-info/RECORD
