Metadata-Version: 2.4
Name: virt-firmware
Version: 25.12
Summary: tools for virtual machine firmware volumes
Author: Gerd Hoffmann
Author-email: kraxel@redhat.com
License: GPLv2
Project-URL: GitLab, https://gitlab.com/kraxel/virt-firmware
Keywords: ovmf,armvirt,edk2,aws,uki
License-File: LICENSE
Requires-Dist: setuptools; python_version < "3.13"
Requires-Dist: cryptography
Requires-Dist: pefile
Dynamic: license-file
